lotl.py
lotl-0.3.0.dist-info/licenses/LICENSE
lotl-0.3.0.dist-info/METADATA
lotl-0.3.0.dist-info/WHEEL
lotl-0.3.0.dist-info/top_level.txt
lotl-0.3.0.dist-info/RECORD
