Metadata-Version: 2.4
Name: lotl
Version: 0.3.0
Summary: lotl is an experimental data science library!
Author: Invizabel
Project-URL: Homepage, https://github.com/Invizabel/lotl
Project-URL: Bug Tracker, https://github.com/Invizabel/lotl/issues
Classifier: Programming Language :: Python :: 3
Classifier: License :: OSI Approved :: MIT License
Classifier: Operating System :: OS Independent
Requires-Python: >=3.7
License-File: LICENSE
Dynamic: license-file
